urify/__init__.py
urify/__main__.py
urify/cli/__init__.py
urify/cli/base.py
urify/core/__init__.py
urify/core/processor.py
urify/core/schema.py
urify-0.2.0.dist-info/entry_points.txt
urify-0.2.0.dist-info/METADATA
urify-0.2.0.dist-info/WHEEL
urify-0.2.0.dist-info/RECORD
