Metadata-Version: 2.1
Name: urify
Version: 0.2.0
Summary: Dissect and filter URLs provided on stdin.
Author: Harsh Verma
Author-email: synacktra.work@gmail.com
Requires-Python: >=3.10,<4.0
Classifier: Programming Language :: Python :: 3
Classifier: Programming Language :: Python :: 3.10
Classifier: Programming Language :: Python :: 3.11
Requires-Dist: pydantic (>=2.4.2,<3.0.0)
Requires-Dist: tldextract (>=5.0.1,<6.0.0)
